plyfile-1.1.1.dist-info/METADATA
plyfile-1.1.1.dist-info/WHEEL
plyfile-1.1.1.dist-info/entry_points.txt
plyfile-1.1.1.dist-info/licenses/COPYING
plyfile.py
plyfile-1.1.1.dist-info/RECORD
