Metadata-Version: 2.1
Name: plyfile
Version: 1.1.1
Summary: PLY file reader/writer
Keywords: ply,numpy
Author-Email: Darsh Ranjan <dranjan@berkeley.edu>
License:                     GNU GENERAL PUBLIC LICENSE
Classifier: Development Status :: 5 - Production/Stable
Classifier: License :: OSI Approved :: GNU General Public License v3 or later (GPLv3+)
Classifier: Operating System :: OS Independent
Classifier: Programming Language :: Python :: 3
Classifier: Programming Language :: Python :: 3.9
Classifier: Programming Language :: Python :: 3.10
Classifier: Programming Language :: Python :: 3.11
Classifier: Programming Language :: Python :: 3.12
Classifier: Topic :: Scientific/Engineering
Project-URL: Homepage, https://github.com/dranjan/python-plyfile
Project-URL: Documentation, https://python-plyfile.readthedocs.io
Project-URL: Repository, https://github.com/dranjan/python-plyfile
Requires-Python: >=3.9
Requires-Dist: numpy>=1.21
